opylib/__init__.py
opylib/csv.py
opylib/data_import_export.py
opylib/datetime_sup.py
opylib/db_cache.py
opylib/dict_persistent.py
opylib/dict_tools.py
opylib/files_folders.py
opylib/list_tools.py
opylib/log.py
opylib/main_runner.py
opylib/notify.py
opylib/rate_limited_execution.py
opylib/replit_support.py
opylib/shuffle.py
opylib/stopwatch.py
opylib/str_parse.py
opylib/streaming.py
opylib/sys_tools.py
opylib/timer.py
opylib-0.9.0.dist-info/LICENSE
opylib-0.9.0.dist-info/METADATA
opylib-0.9.0.dist-info/WHEEL
opylib-0.9.0.dist-info/top_level.txt
opylib-0.9.0.dist-info/RECORD
