Metadata-Version: 2.1
Name: opylib
Version: 0.9.0
Summary: My frequently used classes and functions
Home-page: https://github.com/c-git/opylib
Author: One
Author-email: one.bgz1@gmail.com
Project-URL: Bug Tracker, https://github.com/c-git/opylib/issues
Classifier: Programming Language :: Python :: 3
Classifier: License :: OSI Approved :: MIT License
Classifier: Operating System :: OS Independent
Requires-Python: >=3.6
License-File: LICENSE
Requires-Dist: PyYAML ~=6.0
